{
  "sample_id": "malkg__201305CIRCLMiniDuke.txt",
  "sample_index": 130,
  "source": "malkg",
  "file_name": "201305CIRCLMiniDuke.txt",
  "method_name": "KnowGL",
  "method_file": "Approach_knowgl.py",
  "approach_instance_key": "Approach_knowgl__799485be3cdf7d2b",
  "generation": {
    "status": "success",
    "wall_seconds": 6.271968472913566,
    "attempt_count": 1,
    "model": "Unknown",
    "backend_type": "native",
    "token": 32768,
    "temperature": null
  },
  "parser": {
    "name": "method_internal_parser",
    "success": true
  },
  "generated_graph": {
    "entities": [],
    "relations": [
      {
        "sub": "Miniduke",
        "rel": "subclass of",
        "obj": "TLP"
      },
      {
        "sub": "Executive summary",
        "rel": "subclass of",
        "obj": "Summation"
      },
      {
        "sub": "Bodyswap",
        "rel": "instance of",
        "obj": "video game"
      },
      {
        "sub": "4.3 Implemented commands",
        "rel": "followed by",
        "obj": "4.4 Control"
      },
      {
        "sub": "4.5.1 Network",
        "rel": "instance of",
        "obj": "Network"
      },
      {
        "sub": "4.5.2 Registry",
        "rel": "instance of",
        "obj": "Registry"
      },
      {
        "sub": "4.4.7 Execution process",
        "rel": "instance of",
        "obj": "Execution process"
      },
      {
        "sub": "Network infrastructure",
        "rel": "subclass of",
        "obj": "indicators information"
      },
      {
        "sub": "Sample B",
        "rel": "instance of",
        "obj": "Interesting code"
      },
      {
        "sub": "registry key",
        "rel": "uses",
        "obj": "Decrypt"
      },
      {
        "sub": "Internet connect",
        "rel": "part of",
        "obj": "5.3 evaluate commands"
      },
      {
        "sub": "Miniduke",
        "rel": "instance of",
        "obj": "malware"
      },
      {
        "sub": "report",
        "rel": "author",
        "obj": "Kaspersky"
      },
      {
        "sub": "SHA-256",
        "rel": "based on",
        "obj": "SHA1"
      },
      {
        "sub": "CIRCL",
        "rel": "headquarters location",
        "obj": "Luxembourg"
      },
      {
        "sub": "as-is",
        "rel": "different from",
        "obj": "as-is"
      },
      {
        "sub": "WHITE",
        "rel": "subclass of",
        "obj": "classiﬁed"
      },
      {
        "sub": "Sample B",
        "rel": "part of",
        "obj": "analysis"
      },
      {
        "sub": "dynamic analysis",
        "rel": "subclass of",
        "obj": "analysis"
      },
      {
        "sub": "static analysis",
        "rel": "subclass of",
        "obj": "analysis"
      },
      {
        "sub": "malware",
        "rel": "subclass of",
        "obj": "interpretation"
      },
      {
        "sub": "Google",
        "rel": "instance of",
        "obj": "domain"
      },
      {
        "sub": "protocol",
        "rel": "part of",
        "obj": "malware"
      },
      {
        "sub": "CIRCL - Computer Incident Response Center Luxembourg",
        "rel": "headquarters location",
        "obj": "Luxembourg"
      },
      {
        "sub": "f e e d",
        "rel": "part of",
        "obj": "news"
      },
      {
        "sub": "Google News",
        "rel": "instance of",
        "obj": "website"
      },
      {
        "sub": "i",
        "rel": "instance of",
        "obj": "variable part"
      },
      {
        "sub": "news",
        "rel": "subclass of",
        "obj": "website"
      },
      {
        "sub": "Mozilla",
        "rel": "instance of",
        "obj": "User agent"
      },
      {
        "sub": "4.6 Persistency No persistency No persistency mechanisms",
        "rel": "instance of",
        "obj": "persistency mechanisms"
      },
      {
        "sub": "stage 2",
        "rel": "part of",
        "obj": "Miniduke"
      },
      {
        "sub": "enc_wininet_dll",
        "rel": "part of",
        "obj": "wininet"
      },
      {
        "sub": "hModule",
        "rel": "part of",
        "obj": "HttpOpenRequest"
      },
      {
        "sub": "Internet connect",
        "rel": "instance of",
        "obj": "signed int"
      },
      {
        "sub": "5 lstrcpyA",
        "rel": "instance of",
        "obj": "news"
      },
      {
        "sub": "InternetOpen",
        "rel": "instance of",
        "obj": "proxy"
      },
      {
        "sub": "HTTP",
        "rel": "uses",
        "obj": "SERVICE"
      },
      {
        "sub": "news",
        "rel": "uses",
        "obj": "IP"
      },
      {
        "sub": "dvdform",
        "rel": "instance of",
        "obj": "domains"
      },
      {
        "sub": "2 3 d e x t e r s e a s o n",
        "rel": "instance of",
        "obj": "t e r s e a s o n"
      },
      {
        "sub": "d e x t e r s e a s o n",
        "rel": "part of",
        "obj": "d e x t e r s e a s o n"
      },
      {
        "sub": "Babylearningdvd",
        "rel": "owned by",
        "obj": "babylearningdvd"
      },
      {
        "sub": "2 3 3 t u r b o f i r e c o u p o n",
        "rel": "instance of",
        "obj": "b o f i r e c o u p o n"
      },
      {
        "sub": "t u r b o f i r e c o u p o n",
        "rel": "part of",
        "obj": "t u r b o f i r e c o u p o n"
      },
      {
        "sub": "2 3 s m a l l l v i l l e d v d s e t",
        "rel": "instance of",
        "obj": "m a l l v i l l e d v d s e t"
      },
      {
        "sub": "miamivicedvdboxset",
        "rel": "subclass of",
        "obj": "boxset"
      },
      {
        "sub": "miamivicedvdboxset",
        "rel": "instance of",
        "obj": "boxset"
      },
      {
        "sub": "sexandthecityondvd",
        "rel": "owned by",
        "obj": "cityondvd"
      },
      {
        "sub": "Sherlockholmesondvd",
        "rel": "headquarters location",
        "obj": "Helsinki"
      },
      {
        "sub": "2 3 3 t r x f o r c e k i t o r i g i n a l",
        "rel": "instance of",
        "obj": "f o r c e k i t o r i g i n a l"
      },
      {
        "sub": "t r x f o r c e k i t o r i g i n a l",
        "rel": "instance of",
        "obj": "t r x f o r c e k i t o r i g i n a l"
      },
      {
        "sub": "2 3 weddingdressestoday",
        "rel": "owned by",
        "obj": "weddingdressestoday"
      },
      {
        "sub": "Maxheadroom",
        "rel": "part of the series",
        "obj": "dvdseries"
      },
      {
        "sub": "Panamaserver",
        "rel": "instance of",
        "obj": "IP address"
      },
      {
        "sub": "gbpranking",
        "rel": "uses",
        "obj": "web"
      },
      {
        "sub": "BGP Ranking",
        "rel": "facet of",
        "obj": "bulletproof hoster"
      },
      {
        "sub": "1 20110118",
        "rel": "instance of",
        "obj": "ISPs"
      },
      {
        "sub": "Columbus network",
        "rel": "instance of",
        "obj": "network"
      },
      {
        "sub": "0 / 2 4 − Advanced Communication Network",
        "rel": "part of",
        "obj": "S.A."
      },
      {
        "sub": "WHOIS Panamaserver",
        "rel": "instance of",
        "obj": "inetnum"
      },
      {
        "sub": "Panamaserver",
        "rel": "instance of",
        "obj": "40/21 status"
      },
      {
        "sub": "Ch Group Corp.",
        "rel": "owner of",
        "obj": "Ch Group Corp."
      },
      {
        "sub": "Panama",
        "rel": "contains administrative territorial entity",
        "obj": "El cangrejo"
      },
      {
        "sub": "Panama",
        "rel": "capital",
        "obj": "Panama"
      }
    ]
  }
}